MANIFEST.in
README.txt
setup.py
django_table_prefix.egg-info/PKG-INFO
django_table_prefix.egg-info/SOURCES.txt
django_table_prefix.egg-info/dependency_links.txt
django_table_prefix.egg-info/top_level.txt
table_prefix/__init__.py
table_prefix/models.py
table_prefix/utils.py