Metadata-Version: 1.0
Name: django-table-prefix
Version: 0.0.5
Summary: experimental application for making table prefixes fortables that django creates
Home-page: UNKNOWN
Author: Egor V. Nazarkin, Vitaliy Kucheraviy
Author-email: nimnull@gmail.com
License: BSD
Platform: UNKNOWN
